rightfoot/__init__.py
rightfoot/api/__init__.py
rightfoot/api/rightfoot_api.py
rightfoot/api_client.py
rightfoot/configuration.py
rightfoot/models/__init__.py
rightfoot/models/add_credit_card_to_beneficiary_request.py
rightfoot/models/add_credit_card_to_beneficiary_response.py
rightfoot/models/add_plaid_student_loan_data_to_beneficiary_request.py
rightfoot/models/add_plaid_student_loan_data_to_beneficiary_response.py
rightfoot/models/add_plaid_token_to_beneficiary_request.py
rightfoot/models/add_plaid_token_to_beneficiary_response.py
rightfoot/models/any_ofbody.py
rightfoot/models/benefactor.py
rightfoot/models/benefactor_document.py
rightfoot/models/beneficiary.py
rightfoot/models/body.py
rightfoot/models/cancel_payment_response.py
rightfoot/models/create_ach_credit_funding_source_for_benefactor_response.py
rightfoot/models/create_ach_credit_funding_source_for_organization_response.py
rightfoot/models/create_benefactor_request.py
rightfoot/models/create_benefactor_response.py
rightfoot/models/create_beneficiary_request.py
rightfoot/models/create_beneficiary_response.py
rightfoot/models/create_funding_source_for_benefactor_with_dwolla_token_request.py
rightfoot/models/create_funding_source_for_benefactor_with_micro_deposit_request.py
rightfoot/models/create_funding_source_for_benefactor_with_plaid_token_request.py
rightfoot/models/create_funding_source_for_beneficiary_with_dwolla_token_request.py
rightfoot/models/create_funding_source_for_beneficiary_with_plaid_token_request.py
rightfoot/models/create_funding_source_for_organization_with_dwolla_request.py
rightfoot/models/create_funding_source_for_organization_with_micro_deposit_request.py
rightfoot/models/create_funding_source_for_organization_with_plaid_token_request.py
rightfoot/models/create_funding_source_request.py
rightfoot/models/create_funding_source_response.py
rightfoot/models/create_payment_request.py
rightfoot/models/create_payment_response.py
rightfoot/models/delete_loan_response.py
rightfoot-1.3.4.dist-info/METADATA
rightfoot-1.3.4.dist-info/RECORD
rightfoot-1.3.4.dist-info/WHEEL
site-packages/certifi-2022.9.24.dist-info/INSTALLER
site-packages/certifi-2022.9.24.dist-info/LICENSE
site-packages/certifi-2022.9.24.dist-info/METADATA
site-packages/certifi-2022.9.24.dist-info/WHEEL
site-packages/certifi-2022.9.24.dist-info/top_level.txt
site-packages/chardet-3.0.4.dist-info/DESCRIPTION.rst
site-packages/chardet-3.0.4.dist-info/INSTALLER
site-packages/chardet-3.0.4.dist-info/METADATA
site-packages/chardet-3.0.4.dist-info/WHEEL
site-packages/chardet-3.0.4.dist-info/entry_points.txt
site-packages/chardet-3.0.4.dist-info/metadata.json
site-packages/chardet-3.0.4.dist-info/top_level.txt
site-packages/charset_normalizer-2.0.12.dist-info/INSTALLER
site-packages/charset_normalizer-2.0.12.dist-info/LICENSE
site-packages/charset_normalizer-2.0.12.dist-info/METADATA
site-packages/charset_normalizer-2.0.12.dist-info/WHEEL
site-packages/charset_normalizer-2.0.12.dist-info/entry_points.txt
site-packages/charset_normalizer-2.0.12.dist-info/top_level.txt
site-packages/idna-2.8.dist-info/INSTALLER
site-packages/idna-2.8.dist-info/LICENSE.rst
site-packages/idna-2.8.dist-info/METADATA
site-packages/idna-2.8.dist-info/WHEEL
site-packages/idna-2.8.dist-info/top_level.txt
site-packages/requests-2.27.1.dist-info/INSTALLER
site-packages/requests-2.27.1.dist-info/LICENSE
site-packages/requests-2.27.1.dist-info/METADATA
site-packages/requests-2.27.1.dist-info/WHEEL
site-packages/requests-2.27.1.dist-info/top_level.txt
site-packages/six-1.16.0.dist-info/INSTALLER
site-packages/six-1.16.0.dist-info/LICENSE
site-packages/six-1.16.0.dist-info/METADATA
site-packages/six-1.16.0.dist-info/WHEEL
site-packages/six-1.16.0.dist-info/top_level.txt
site-packages/urllib3-1.25.11.dist-info/INSTALLER
site-packages/urllib3-1.25.11.dist-info/LICENSE.txt
site-packages/urllib3-1.25.11.dist-info/METADATA
site-packages/urllib3-1.25.11.dist-info/WHEEL
site-packages/urllib3-1.25.11.dist-info/top_level.txt
