Metadata-Version: 2.1
Name: rightfoot
Version: 1.3.4
Author-email: will@rightfoot.com
Home-page: https://rightfoot.com
License: MIT
Requires-Dist: urllib3 >= 1.15
Requires-Dist: six >= 1.10
Requires-Dist: certifi
Requires-Dist: python-dateutil
